<?xml version="1.0" encoding="utf-8" ?>
<dwsync>
<file name="bg_box1.png" server="edtech2.boisestate.edu//" local="129459950920000000" remote="131665120800000000" Dst="2" />
<file name="bg_form.png" server="edtech2.boisestate.edu//" local="129460049260000000" remote="131665120800000000" Dst="2" />
<file name="bg_pagination.png" server="edtech2.boisestate.edu//" local="129459933400000000" remote="131665120800000000" Dst="2" />
<file name="bg_slider.png" server="edtech2.boisestate.edu//" local="129459930480000000" remote="131665120800000000" Dst="2" />
<file name="big_img1.jpg" server="edtech2.boisestate.edu//" local="129460091300000000" remote="131665120800000000" Dst="2" />
<file name="big_img2.jpg" server="edtech2.boisestate.edu//" local="129460091400000000" remote="131665120800000000" Dst="2" />
<file name="big_img3.jpg" server="edtech2.boisestate.edu//" local="129460091480000000" remote="131665120800000000" Dst="2" />
<file name="bg.jpg" server="edtech2.boisestate.edu//" local="129459936680000000" remote="131665120800000000" Dst="2" />
<file name="big_img4.jpg" server="edtech2.boisestate.edu//" local="129460091540000000" remote="131665120800000000" Dst="2" />
<file name="big_img6.jpg" server="edtech2.boisestate.edu//" local="129460091660000000" remote="131665120800000000" Dst="2" />
<file name="big_img5.jpg" server="edtech2.boisestate.edu//" local="129460091600000000" remote="131665120800000000" Dst="2" />
<file name="buttons.png" server="edtech2.boisestate.edu//" local="129459933160000000" remote="131665120800000000" Dst="2" />
<file name="icon1.jpg" server="edtech2.boisestate.edu//" local="129459926780000000" remote="131665120800000000" Dst="2" />
<file name="icon2.jpg" server="edtech2.boisestate.edu//" local="129459926780000000" remote="131665120800000000" Dst="2" />
<file name="icon4.jpg" server="edtech2.boisestate.edu//" local="129459926780000000" remote="131665120800000000" Dst="2" />
<file name="icon3.jpg" server="edtech2.boisestate.edu//" local="129459926780000000" remote="131665120800000000" Dst="2" />
<file name="icon5.jpg" server="edtech2.boisestate.edu//" local="129459926780000000" remote="131665120800000000" Dst="2" />
<file name="img2.jpg" server="edtech2.boisestate.edu//" local="129459933860000000" remote="131665120800000000" Dst="2" />
<file name="img3.jpg" server="edtech2.boisestate.edu//" local="129459933960000000" remote="131665120800000000" Dst="2" />
<file name="img1.jpg" server="edtech2.boisestate.edu//" local="129459933700000000" remote="131665120800000000" Dst="2" />
<file name="img4.jpg" server="edtech2.boisestate.edu//" local="129459934060000000" remote="131665120800000000" Dst="2" />
<file name="img5.jpg" server="edtech2.boisestate.edu//" local="129459934200000000" remote="131665120800000000" Dst="2" />
<file name="logo.jpg" server="edtech2.boisestate.edu//" local="129459926780000000" remote="131665120800000000" Dst="2" />
<file name="latest_works.png" server="edtech2.boisestate.edu//" local="129459928160000000" remote="131665120800000000" Dst="2" />
<file name="magnify.png" server="edtech2.boisestate.edu//" local="129304373440000000" remote="131665120800000000" Dst="2" />
<file name="marker_1.gif" server="edtech2.boisestate.edu//" local="129459926960000000" remote="131665120800000000" Dst="2" />
<file name="marker_2.png" server="edtech2.boisestate.edu//" local="129460048380000000" remote="131665120800000000" Dst="2" />
<file name="marker_3.png" server="edtech2.boisestate.edu//" local="129460048940000000" remote="131665120800000000" Dst="2" />
<file name="marker_left.png" server="edtech2.boisestate.edu//" local="129460028040000000" remote="131665120800000000" Dst="2" />
<file name="marker_right.png" server="edtech2.boisestate.edu//" local="129460027180000000" remote="131665120800000000" Dst="2" />
<file name="newsletter_bg.png" server="edtech2.boisestate.edu//" local="129459932660000000" remote="131665120800000000" Dst="2" />
<file name="page1_img1.png" server="edtech2.boisestate.edu//" local="129459927680000000" remote="131665120800000000" Dst="2" />
<file name="page1_img2.png" server="edtech2.boisestate.edu//" local="129459927680000000" remote="131665120800000000" Dst="2" />
<file name="page1_img3.png" server="edtech2.boisestate.edu//" local="129459931860000000" remote="131665120800000000" Dst="2" />
<file name="page1_img4.png" server="edtech2.boisestate.edu//" local="129459931860000000" remote="131665120800000000" Dst="2" />
<file name="page1_img5.png" server="edtech2.boisestate.edu//" local="129459931860000000" remote="131665120800000000" Dst="2" />
<file name="page1_img6.png" server="edtech2.boisestate.edu//" local="129459931860000000" remote="131665120800000000" Dst="2" />
<file name="page2_img1.png" server="edtech2.boisestate.edu//" local="129460048000000000" remote="131665120800000000" Dst="2" />
<file name="page2_img2.png" server="edtech2.boisestate.edu//" local="129460048200000000" remote="131665120800000000" Dst="2" />
<file name="page2_img3.png" server="edtech2.boisestate.edu//" local="129460062120000000" remote="131665120800000000" Dst="2" />
<file name="page3_img1.png" server="edtech2.boisestate.edu//" local="129460048940000000" remote="131665120800000000" Dst="2" />
<file name="page3_img2.png" server="edtech2.boisestate.edu//" local="129460048940000000" remote="131665120800000000" Dst="2" />
<file name="page3_img3.png" server="edtech2.boisestate.edu//" local="129460048940000000" remote="131665120800000000" Dst="2" />
<file name="page3_img4.png" server="edtech2.boisestate.edu//" local="129460048960000000" remote="131665120800000000" Dst="2" />
<file name="page3_img5.png" server="edtech2.boisestate.edu//" local="129460048960000000" remote="131665120800000000" Dst="2" />
<file name="page3_img6.png" server="edtech2.boisestate.edu//" local="129460048960000000" remote="131665120800000000" Dst="2" />
<file name="send_button.png" server="edtech2.boisestate.edu//" local="129460106440000000" remote="131665120800000000" Dst="2" />
<file name="tweets.png" server="edtech2.boisestate.edu//" local="129459928400000000" remote="131665120800000000" Dst="2" />
</dwsync>